freeswitch_exporter/__init__.py
freeswitch_exporter/cli.py
freeswitch_exporter/collector.py
freeswitch_exporter/esl.py
freeswitch_exporter/http.py
prometheus_freeswitch_exporter-1.0.1.dist-info/LICENSE
prometheus_freeswitch_exporter-1.0.1.dist-info/METADATA
prometheus_freeswitch_exporter-1.0.1.dist-info/WHEEL
prometheus_freeswitch_exporter-1.0.1.dist-info/entry_points.txt
prometheus_freeswitch_exporter-1.0.1.dist-info/top_level.txt
prometheus_freeswitch_exporter-1.0.1.dist-info/RECORD
