Metadata-Version: 2.1
Name: prometheus-freeswitch-exporter
Version: 1.0.1
Summary: FreeSWITCH exporter for the Prometheus monitoring system.
Home-page: https://github.com/znerol/prometheus-freeswitch-exporter
Author: Lorenz Schori
Author-email: lo@znerol.ch
License: Apache Software License 2.0
Keywords: prometheus exporter network monitoring voip
Platform: UNKNOWN
Classifier: Development Status :: 3 - Alpha
Classifier: Intended Audience :: Information Technology
Classifier: Intended Audience :: System Administrators
Classifier: Topic :: System :: Monitoring
Classifier: Topic :: System :: Networking :: Monitoring
Classifier: License :: OSI Approved :: Apache Software License
Requires-Dist: Werkzeug
Requires-Dist: asgiref
Requires-Dist: prometheus-client (>=0.0.11)
Requires-Dist: pyyaml
Requires-Dist: requests
